design/mux4_to_1/mux4_to_1.v
`timescale 1ns/1ns

module mux4_to_1(/*autoarg*/
   // Outputs
   z,
   // Inputs
   din, sel
   );
   input [3:0] din;
   input [1:0] sel;
   output  reg   z;

   always@(*)
     begin
	case(sel)
	  2'h0 : z = din[0];
	  2'h1 : z = din[1];
	  2'h2 : z = din[2];
	  2'h3 : z = din[3];
	  default : z = 1'h0;
	endcase // case (sel)
     end
endmodule // mux4_to_1
// Local Variable:
// verilog-library-directories:("~/Projects/FPGA_Projects/iVerilog/design")
// End:

design/mux8_to_1/mux8_to_1.v
`timescale 1ns/1ns

module mux8_to_1(/*AUTOARG*/
   // Outputs
   z,
   // Inputs
   din, sel
   );
   input [7:0] din;
   input [2:0] sel;
   output  z;
   
/*AUTOREG*/ 
/*AUTOWIRE*/

   wire        temp1, temp2;
   
 
   mux4_to_1 m1 (/*AUTOINST*/
		 // Outputs
		 .z			(temp1),
		 // Inputs
		 .din			(din[3:0]),
		 .sel			(sel[1:0]));
   mux4_to_1 m2 (/*AUTOINST*/
		 // Outputs
		 .z			(temp2),
		 // Inputs
		 .din			(din[7:4]),
		 .sel			(sel[1:0]));

   assign z = sel[2] ? temp2 : temp1;
   
endmodule 
// Local Variables: 
// verilog-library-directories:("~/Projects/FPGA_Projects/iVerilog/design/mux4_to_1/" ".") 
// End:

tb_design/tb_mux8_to_1/tb_mux8_to_1.v
`timescale 1ns/1ns

module tb_mux8_to_1(); 
/*AUTOREG*/ 
/*AUTOWIRE*/ 
// Beginning of automatic wires (for undeclared instantiated-module outputs)
wire			z;			// From DUT of mux8_to_1.v
// End of automatics
   reg [7:0] 		din;
   reg [2:0] 		sel;
 
mux8_to_1 DUT (/*AUTOINST*/
	       // Outputs
	       .z			(z),
	       // Inputs
	       .din			(din[7:0]),
	       .sel			(sel[2:0])); 
   initial sel[0] = 0;
   always #5 sel[0] = ~sel[0];

   initial sel[1] = 0;
   always #10 sel[1] = ~sel[1];

   initial sel[2] = 0;
   always #15 sel[2] = ~sel[2];
   

   initial begin
      din = 8'haa;
      #15
	din = 8'h4f;
      #15
	din = 8'hff;
      #15
	din = 8'hf5;
      $finish;
    end
	  
initial begin 
$dumpfile("tb_mux8_to_1.vcd"); 
$dumpvars(0,tb_mux8_to_1); 
end 
endmodule 
// Local Variables: 
// verilog-library-directories:("/home/kiran/Projects/fpgaProjects/iVerilog/design/mux8_to_1/" "~/Projects/fpgaProjects/iVerilog/design/mux4_to_1/" ".") 
// End:

tb_design/tb_mux8_to_1/tb_mux8_to_1.vcd
$date
	Wed Dec 13 13:58:43 2023
$end
$version
	Icarus Verilog
$end
$timescale
	1ns
$end
$scope module tb_mux8_to_1 $end
$var wire 1 ! z $end
$var reg 8 " din [7:0] $end
$var reg 3 # sel [2:0] $end
$scope module DUT $end
$var wire 8 $ din [7:0] $end
$var wire 3 % sel [2:0] $end
$var wire 1 ! z $end
$var wire 1 & temp2 $end
$var wire 1 ' temp1 $end
$scope module m1 $end
$var wire 4 ( din [3:0] $end
$var wire 2 ) sel [1:0] $end
$var reg 1 ' z $end
$upscope $end
$scope module m2 $end
$var wire 4 * din [3:0] $end
$var wire 2 + sel [1:0] $end
$var reg 1 & z $end
$upscope $end
$upscope $end
$upscope $end
$enddefinitions $end
#0
$dumpvars
b0 +
b1010 *
b0 )
b1010 (
0'
0&
b0 %
b10101010 $
b0 #
b10101010 "
0!
$end
#5
1!
1'
1&
b1 )
b1 +
b1 #
b1 %
#10
0!
0'
0&
b10 )
b10 +
b10 #
b10 %
#15
1'
b11 )
b11 +
b1111 (
b100 *
b1001111 "
b1001111 $
b111 #
b111 %
#20
b0 )
b0 +
b100 #
b100 %
#25
b1 )
b1 +
b101 #
b101 %
#30
1&
1!
b10 )
b10 +
b1111 *
b11111111 "
b11111111 $
b10 #
b10 %
#35
b11 )
b11 +
b11 #
b11 %
#40
b0 )
b0 +
b0 #
b0 %
#45
0'
b1 )
b1 +
b101 (
b11110101 "
b11110101 $
b101 #
b101 %
