design/mux4_to_1/mux4_to_1.v
`timescale 1ns/1ns

module mux4_to_1(/*autoarg*/
   // Outputs
   z,
   // Inputs
   din, sel
   );
   input [3:0] din;
   input [1:0] sel;
   output  reg   z;

   always@(*)
     begin
	case(sel)
	  2'h0 : z = din[0];
	  2'h1 : z = din[1];
	  2'h2 : z = din[2];
	  2'h3 : z = din[3];
	  default : z = 1'h0;
	endcase // case (sel)
     end
endmodule // mux4_to_1
// Local Variable:
// verilog-library-directories:("~/Projects/FPGA_Projects/iVerilog/design")
// End:

tb_design/tb_mux4_to_1/tb_mux4_to_1.v
module tb_mux4_to_1(); 
/*AUTOREG*/ 
/*AUTOWIRE*/ 
// Beginning of automatic wires (for undeclared instantiated-module outputs)
wire			z;			// From DUT of mux4_to_1.v
// End of automatics
reg [3:0] din; 
reg [1:0] sel;
 
mux4_to_1 DUT (/*AUTOINST*/
	       // Outputs
	       .z			(z),
	       // Inputs
	       .din			(din[3:0]),
	       .sel			(sel[1:0])); 

  initial sel[0] = 0;  
  always #5 sel[0] = ~sel[0];

   initial sel[1] = 0;
   always #10 sel[1] = ~sel[1];

   initial begin
      din = 4'hb;
      #40
	din = 4'h3;
      #40
	din = 4'hf;
      #40
	din = 4'h6;
      $finish;
   end
   
initial begin 
$dumpfile("tb_mux4_to_1.vcd"); 
$dumpvars(0,tb_mux4_to_1); 
end 
endmodule 
// Local Variables: 
// verilog-library-directories:("~/Projects/fpgaProjects/iVerilog/design/mux4_to_1/") 
// End:

tb_design/tb_mux4_to_1/tb_mux4_to_1.vcd
$date
	Mon Dec 11 23:52:11 2023
$end
$version
	Icarus Verilog
$end
$timescale
	1ns
$end
$scope module tb_mux4_to_1 $end
$var wire 1 ! z $end
$var reg 4 " din [3:0] $end
$var reg 2 # sel [1:0] $end
$scope module DUT $end
$var wire 4 $ din [3:0] $end
$var wire 2 % sel [1:0] $end
$var reg 1 ! z $end
$upscope $end
$upscope $end
$enddefinitions $end
#0
$dumpvars
b0 %
b1011 $
b0 #
b1011 "
1!
$end
#5
b1 #
b1 %
#10
0!
b10 #
b10 %
#15
1!
b11 #
b11 %
#20
b0 #
b0 %
#25
b1 #
b1 %
#30
0!
b10 #
b10 %
#35
1!
b11 #
b11 %
#40
b0 #
b0 %
b11 "
b11 $
#45
b1 #
b1 %
#50
0!
b10 #
b10 %
#55
b11 #
b11 %
#60
1!
b0 #
b0 %
#65
b1 #
b1 %
#70
0!
b10 #
b10 %
#75
b11 #
b11 %
#80
1!
b0 #
b0 %
b1111 "
b1111 $
#85
b1 #
b1 %
#90
b10 #
b10 %
#95
b11 #
b11 %
#100
b0 #
b0 %
#105
b1 #
b1 %
#110
b10 #
b10 %
#115
b11 #
b11 %
#120
0!
b0 #
b0 %
b110 "
b110 $
